{
  "metadata": {
    "updated": "2026-03-18T01:17:38",
    "updated_display": "18.03.2026 01:17",
    "total_analyzed": 10,
    "failed": 0,
    "rsl_period_days": 26
  },
  "stats": {
    "avg_rsl": 0.9913,
    "median_rsl": 0.9877,
    "max_rsl": 1.03,
    "max_ticker": "AMZN",
    "min_rsl": 0.9607,
    "min_ticker": "META",
    "bullish_count": 3,
    "bearish_count": 7,
    "returns_avg": {
      "26t": -2.38,
      "1m": -0.83,
      "3m": -4.41,
      "6m": 3.87
    }
  },
  "rankings": [
    {
      "rank": 1,
      "ticker": "AMZN",
      "company": "AMZN",
      "sector": "Diverse",
      "rsl": 1.03,
      "percentile": 100.0,
      "price": 215.2,
      "change_26t": 3.1,
      "change_1m": 5.08,
      "change_3m": -5.1,
      "change_6m": -6.57,
      "pct_over_ma50": -3.37,
      "pct_over_ma200": -4.26,
      "pct_from_high": -15.28,
      "vol_ratio": 0.76,
      "rel_vs_spx": 6.67,
      "beta": 1.42,
      "pe_ratio": 29.47945,
      "div_yield": 0.0
    },
    {
      "rank": 2,
      "ticker": "UNH",
      "company": "UNH",
      "sector": "Diverse",
      "rsl": 1.0135,
      "percentile": 90.0,
      "price": 287.57,
      "change_26t": 5.12,
      "change_1m": 0.56,
      "change_3m": -11.68,
      "change_6m": -15.34,
      "pct_over_ma50": -4.25,
      "pct_over_ma200": -7.25,
      "pct_from_high": -50.68,
      "vol_ratio": 0.68,
      "rel_vs_spx": 8.69,
      "beta": 0.38,
      "pe_ratio": 21.60556,
      "div_yield": 310.0
    },
    {
      "rank": 3,
      "ticker": "GOOGL",
      "company": "GOOGL",
      "sector": "Diverse",
      "rsl": 1.0106,
      "percentile": 80.0,
      "price": 310.92,
      "change_26t": -4.06,
      "change_1m": 2.57,
      "change_3m": 2.87,
      "change_6m": 30.18,
      "pct_over_ma50": -2.39,
      "pct_over_ma200": 20.75,
      "pct_from_high": -9.47,
      "vol_ratio": 0.68,
      "rel_vs_spx": -0.49,
      "beta": 1.112,
      "pe_ratio": 28.239782,
      "div_yield": 27.0
    },
    {
      "rank": 4,
      "ticker": "MSFT",
      "company": "MSFT",
      "sector": "Diverse",
      "rsl": 0.9954,
      "percentile": 70.0,
      "price": 399.41,
      "change_26t": -3.21,
      "change_1m": 0.18,
      "change_3m": -17.29,
      "change_6m": -19.85,
      "pct_over_ma50": -6.15,
      "pct_over_ma200": -16.94,
      "pct_from_high": -26.01,
      "vol_ratio": 0.72,
      "rel_vs_spx": 0.36,
      "beta": 1.108,
      "pe_ratio": 24.99437,
      "div_yield": 91.0
    },
    {
      "rank": 5,
      "ticker": "BRK-B",
      "company": "BRK-B",
      "sector": "Diverse",
      "rsl": 0.994,
      "percentile": 60.0,
      "price": 492.58,
      "change_26t": -1.1,
      "change_1m": -1.3,
      "change_3m": -2.15,
      "change_6m": 0.51,
      "pct_over_ma50": -0.16,
      "pct_over_ma200": 0.22,
      "pct_from_high": -8.75,
      "vol_ratio": 0.72,
      "rel_vs_spx": 2.47,
      "beta": 0.688,
      "pe_ratio": 15.848777,
      "div_yield": 0.0
    },
    {
      "rank": 6,
      "ticker": "NVDA",
      "company": "NVDA",
      "sector": "Diverse",
      "rsl": 0.9814,
      "percentile": 50.0,
      "price": 181.93,
      "change_26t": -4.26,
      "change_1m": -3.21,
      "change_3m": 4.48,
      "change_6m": 2.61,
      "pct_over_ma50": -1.79,
      "pct_over_ma200": 2.31,
      "pct_from_high": -12.12,
      "vol_ratio": 0.95,
      "rel_vs_spx": -0.69,
      "beta": 2.375,
      "pe_ratio": 37.434155,
      "div_yield": 2.0
    },
    {
      "rank": 7,
      "ticker": "TSLA",
      "company": "TSLA",
      "sector": "Diverse",
      "rsl": 0.9813,
      "percentile": 40.0,
      "price": 399.27,
      "change_26t": -4.33,
      "change_1m": -2.93,
      "change_3m": -17.4,
      "change_6m": 14.8,
      "pct_over_ma50": -4.66,
      "pct_over_ma200": 1.38,
      "pct_from_high": -18.5,
      "vol_ratio": 0.95,
      "rel_vs_spx": -0.76,
      "beta": 1.926,
      "pe_ratio": 369.69443,
      "div_yield": 0.0
    },
    {
      "rank": 8,
      "ticker": "JNJ",
      "company": "JNJ",
      "sector": "Diverse",
      "rsl": 0.9804,
      "percentile": 30.0,
      "price": 238.11,
      "change_26t": 0.31,
      "change_1m": -2.29,
      "change_3m": 14.91,
      "change_6m": 37.04,
      "pct_over_ma50": 2.87,
      "pct_over_ma200": 24.4,
      "pct_from_high": -4.2,
      "vol_ratio": 0.74,
      "rel_vs_spx": 3.88,
      "beta": 0.326,
      "pe_ratio": 22.026827,
      "div_yield": 214.0
    },
    {
      "rank": 9,
      "ticker": "AAPL",
      "company": "AAPL",
      "sector": "Diverse",
      "rsl": 0.9653,
      "percentile": 20.0,
      "price": 254.23,
      "change_26t": -7.42,
      "change_1m": -3.83,
      "change_3m": -6.51,
      "change_6m": 12.31,
      "pct_over_ma50": -2.92,
      "pct_over_ma200": 3.45,
      "pct_from_high": -11.08,
      "vol_ratio": 0.67,
      "rel_vs_spx": -3.85,
      "beta": 1.116,
      "pe_ratio": 32.05927,
      "div_yield": 41.0
    },
    {
      "rank": 10,
      "ticker": "META",
      "company": "META",
      "sector": "Diverse",
      "rsl": 0.9607,
      "percentile": 10.0,
      "price": 622.66,
      "change_26t": -7.98,
      "change_1m": -3.11,
      "change_3m": -6.21,
      "change_6m": -17.0,
      "pct_over_ma50": -4.58,
      "pct_over_ma200": -9.79,
      "pct_from_high": -21.0,
      "vol_ratio": 0.86,
      "rel_vs_spx": -4.41,
      "beta": 1.279,
      "pe_ratio": 26.735077,
      "div_yield": 33.0
    }
  ],
  "sectors": [
    {
      "sector": "Diverse",
      "avg_rsl": 0.9913,
      "median_rsl": 0.9877,
      "count": 10,
      "avg_change_26t": -2.38,
      "in_top25": 3,
      "top25_pct": 30.0,
      "best_ticker": "AMZN"
    }
  ]
}